tadc_import_validator/__init__.py
tadc_import_validator/command_line.py
tadc_import_validator/csv_file_validator/CSVFileValidator.py
tadc_import_validator/csv_file_validator/__init__.py
tadc_import_validator/tadc_import_row/TADCImportRow.py
tadc_import_validator/tadc_import_row/__init__.py
tadc_import_validator-0.1.1.dist-info/DESCRIPTION.rst
tadc_import_validator-0.1.1.dist-info/METADATA
tadc_import_validator-0.1.1.dist-info/RECORD
tadc_import_validator-0.1.1.dist-info/WHEEL
tadc_import_validator-0.1.1.dist-info/entry_points.txt
tadc_import_validator-0.1.1.dist-info/metadata.json
tadc_import_validator-0.1.1.dist-info/top_level.txt
