Metadata-Version: 2.0
Name: tadc-import-validator
Version: 0.1.1
Summary: Validates CSV files for use in Talis Aspire Digitised Content data imports
Home-page: http://talis.com
Author: Talis Education Ltd
Author-email: tgh@talis.com
License: MIT
Platform: UNKNOWN
Classifier: Programming Language :: Python
Classifier: Programming Language :: Python :: 2.7
Classifier: Development Status :: 4 - Beta
Classifier: Environment :: Other Environment
Classifier: Intended Audience :: Developers
Classifier: License :: OSI Approved :: MIT License
Classifier: Operating System :: OS Independent
Classifier: Topic :: Software Development :: Libraries :: Python Modules
Classifier: Topic :: Text Processing
Classifier: Natural Language :: English
Requires-Dist: datetime
Requires-Dist: logbook
Requires-Dist: unicodecsv
